compose_me-0.2.0.dist-info/METADATA
compose_me-0.2.0.dist-info/WHEEL
compose_me-0.2.0.dist-info/entry_points.txt
compose_me/__init__.py
compose_me/__main__.py
compose_me/defaults.py
compose_me-0.2.0.dist-info/RECORD
