Metadata-Version: 2.1
Name: compose-me
Version: 0.2.0
Summary: Helm's little sister for Docker Compose.
Author-Email: Niklas Rosenstein <rosensteinniklas@gmail.com>
License: MIT
Requires-Python: >=3.10
Requires-Dist: pyyaml>=6.0.1
Requires-Dist: jinja2>=3.1.2
Requires-Dist: typer>=0.9.0
Requires-Dist: mypy>=1.7.1
Requires-Dist: black>=23.11.0
Requires-Dist: flake8>=6.1.0
